[{
        "domain": null,
        "method": "GET|HEAD",
        "uri": "\/",
        "name": null,
        "action": "App\\Http\\Controllers\\HomeController@index",
        "middleware": "web,canInstall,locale"
    }, {
        "domain": null,
        "method": "GET|HEAD",
        "uri": "add_vehicle",
        "name": null,
        "action": "App\\Http\\Controllers\\DriverDashboardController@add_vehicle",
        "middleware": "web,locale,driver_guest"
    }, {
        "domain": null,
        "method": "GET|HEAD",
        "uri": "admin",
        "name": null,
        "action": "Closure",
        "middleware": "web,admin_guest"
    }, {
        "domain": null,
        "method": "GET|POST|HEAD",
        "uri": "admin\/add_admin_user",
        "name": null,
        "action": "App\\Http\\Controllers\\Admin\\AdminController@add",
        "middleware": "web,admin_guest,admin_can:manage_admin"
    }, {
        "domain": null,
        "method": "GET|POST|HEAD",
        "uri": "admin\/add_car_type",
        "name": null,
        "action": "App\\Http\\Controllers\\Admin\\CarTypeController@add",
        "middleware": "web,admin_guest,admin_can:manage_car_type"
    }, {
        "domain": null,
        "method": "GET|POST|HEAD",
        "uri": "admin\/add_company",
        "name": null,
        "action": "App\\Http\\Controllers\\Admin\\CompanyController@add",
        "middleware": "web,admin_guest,admin_can:add_company"
    }, {
        "domain": null,
        "method": "GET|POST|HEAD",
        "uri": "admin\/add_country",
        "name": null,
        "action": "App\\Http\\Controllers\\Admin\\CountryController@add",
        "middleware": "web,admin_guest,admin_can:manage_country"
    }, {
        "domain": null,
        "method": "GET|POST|HEAD",
        "uri": "admin\/add_currency",
        "name": null,
        "action": "App\\Http\\Controllers\\Admin\\CurrencyController@add",
        "middleware": "web,admin_guest,admin_can:manage_currency"
    }, {
        "domain": null,
        "method": "GET|POST|HEAD",
        "uri": "admin\/add_driver",
        "name": null,
        "action": "App\\Http\\Controllers\\Admin\\DriverController@add",
        "middleware": "web,admin_guest,admin_can:add_driver"
    }, {
        "domain": null,
        "method": "GET|POST|HEAD",
        "uri": "admin\/add_help",
        "name": null,
        "action": "App\\Http\\Controllers\\Admin\\HelpController@add",
        "middleware": "web,admin_guest,admin_can:manage_help"
    }, {
        "domain": null,
        "method": "GET|POST|HEAD",
        "uri": "admin\/add_help_category",
        "name": null,
        "action": "App\\Http\\Controllers\\Admin\\HelpCategoryController@add",
        "middleware": "web,admin_guest,admin_can:manage_help"
    }, {
        "domain": null,
        "method": "GET|POST|HEAD",
        "uri": "admin\/add_help_subcategory",
        "name": null,
        "action": "App\\Http\\Controllers\\Admin\\HelpSubCategoryController@add",
        "middleware": "web,admin_guest,admin_can:manage_help"
    }, {
        "domain": null,
        "method": "GET|POST|HEAD",
        "uri": "admin\/add_language",
        "name": null,
        "action": "App\\Http\\Controllers\\Admin\\LanguageController@add",
        "middleware": "web,admin_guest,admin_can:manage_language"
    }, {
        "domain": null,
        "method": "GET|POST|HEAD",
        "uri": "admin\/add_location",
        "name": null,
        "action": "App\\Http\\Controllers\\Admin\\LocationsController@add",
        "middleware": "web,admin_guest,admin_can:manage_locations"
    }, {
        "domain": null,
        "method": "GET|POST|HEAD",
        "uri": "admin\/add_manage_fare",
        "name": null,
        "action": "App\\Http\\Controllers\\Admin\\ManageFareController@add",
        "middleware": "web,admin_guest,admin_can:manage_peak_based_fare"
    }, {
        "domain": null,
        "method": "GET|POST|HEAD",
        "uri": "admin\/add_page",
        "name": null,
        "action": "App\\Http\\Controllers\\Admin\\PagesController@add",
        "middleware": "web,admin_guest,admin_can:manage_static_pages"
    }, {
        "domain": null,
        "method": "GET|POST|HEAD",
        "uri": "admin\/add_promo_code",
        "name": null,
        "action": "App\\Http\\Controllers\\Admin\\PromocodeController@add",
        "middleware": "web,admin_guest,admin_can:manage_promo_code"
    }, {
        "domain": null,
        "method": "GET|POST|HEAD",
        "uri": "admin\/add_rider",
        "name": null,
        "action": "App\\Http\\Controllers\\Admin\\RiderController@add",
        "middleware": "web,admin_guest,admin_can:add_rider"
    }, {
        "domain": null,
        "method": "GET|POST|HEAD",
        "uri": "admin\/add_role",
        "name": null,
        "action": "App\\Http\\Controllers\\Admin\\RolesController@add",
        "middleware": "web,admin_guest,admin_can:manage_admin"
    }, {
        "domain": null,
        "method": "GET|POST|HEAD",
        "uri": "admin\/add_vehicle",
        "name": null,
        "action": "App\\Http\\Controllers\\Admin\\VehicleController@add",
        "middleware": "web,admin_guest,admin_can:manage_vehicle"
    }, {
        "domain": null,
        "method": "GET|POST|HEAD",
        "uri": "admin\/add_wallet",
        "name": null,
        "action": "App\\Http\\Controllers\\Admin\\WalletController@add",
        "middleware": "web,admin_guest,admin_can:manage_wallet"
    }, {
        "domain": null,
        "method": "GET|HEAD",
        "uri": "admin\/admin_user",
        "name": null,
        "action": "App\\Http\\Controllers\\Admin\\AdminController@view",
        "middleware": "web,admin_guest,admin_can:manage_admin"
    }, {
        "domain": null,
        "method": "POST",
        "uri": "admin\/ajax_help_subcategory\/{id}",
        "name": null,
        "action": "App\\Http\\Controllers\\Admin\\HelpController@ajax_help_subcategory",
        "middleware": "web,admin_guest,admin_can:manage_help"
    }, {
        "domain": null,
        "method": "GET|POST|HEAD",
        "uri": "admin\/api_credentials",
        "name": null,
        "action": "App\\Http\\Controllers\\Admin\\ApiCredentialsController@index",
        "middleware": "web,admin_guest,admin_can:manage_api_credentials"
    }, {
        "domain": null,
        "method": "POST",
        "uri": "admin\/authenticate",
        "name": null,
        "action": "App\\Http\\Controllers\\Admin\\AdminController@authenticate",
        "middleware": "web"
    }, {
        "domain": null,
        "method": "GET|HEAD",
        "uri": "admin\/cancel_trips",
        "name": null,
        "action": "App\\Http\\Controllers\\Admin\\TripsController@cancel_trips",
        "middleware": "web,admin_guest,admin_can:manage_cancel_trips"
    }, {
        "domain": null,
        "method": "GET|HEAD",
        "uri": "admin\/car_type",
        "name": null,
        "action": "App\\Http\\Controllers\\Admin\\CarTypeController@index",
        "middleware": "web,admin_guest,admin_can:manage_car_type"
    }, {
        "domain": null,
        "method": "GET|HEAD",
        "uri": "admin\/company",
        "name": null,
        "action": "App\\Http\\Controllers\\Admin\\CompanyController@index",
        "middleware": "web,admin_guest,admin_can:view_company"
    }, {
        "domain": null,
        "method": "GET|HEAD",
        "uri": "admin\/country",
        "name": null,
        "action": "App\\Http\\Controllers\\Admin\\CountryController@index",
        "middleware": "web,admin_guest,admin_can:manage_country"
    }, {
        "domain": null,
        "method": "GET|HEAD",
        "uri": "admin\/currency",
        "name": null,
        "action": "App\\Http\\Controllers\\Admin\\CurrencyController@index",
        "middleware": "web,admin_guest,admin_can:manage_currency"
    }, {
        "domain": null,
        "method": "GET|HEAD",
        "uri": "admin\/dashboard",
        "name": null,
        "action": "App\\Http\\Controllers\\Admin\\AdminController@index",
        "middleware": "web,admin_guest"
    }, {
        "domain": null,
        "method": "GET|POST|HEAD",
        "uri": "admin\/delete_admin_user\/{id}",
        "name": null,
        "action": "App\\Http\\Controllers\\Admin\\AdminController@delete",
        "middleware": "web,admin_guest,admin_can:manage_admin"
    }, {
        "domain": null,
        "method": "GET|POST|HEAD",
        "uri": "admin\/delete_car_type\/{id}",
        "name": null,
        "action": "App\\Http\\Controllers\\Admin\\CarTypeController@delete",
        "middleware": "web,admin_guest,admin_can:manage_car_type"
    }, {
        "domain": null,
        "method": "GET|POST|HEAD",
        "uri": "admin\/delete_company\/{id}",
        "name": null,
        "action": "App\\Http\\Controllers\\Admin\\CompanyController@delete",
        "middleware": "web,admin_guest,admin_can:delete_company"
    }, {
        "domain": null,
        "method": "GET|HEAD",
        "uri": "admin\/delete_country\/{id}",
        "name": null,
        "action": "App\\Http\\Controllers\\Admin\\CountryController@delete",
        "middleware": "web,admin_guest,admin_can:manage_country"
    }, {
        "domain": null,
        "method": "GET|HEAD",
        "uri": "admin\/delete_currency\/{id}",
        "name": null,
        "action": "App\\Http\\Controllers\\Admin\\CurrencyController@delete",
        "middleware": "web,admin_guest,admin_can:manage_currency"
    }, {
        "domain": null,
        "method": "GET|POST|HEAD",
        "uri": "admin\/delete_driver\/{id}",
        "name": null,
        "action": "App\\Http\\Controllers\\Admin\\DriverController@delete",
        "middleware": "web,admin_guest,admin_can:delete_driver"
    }, {
        "domain": null,
        "method": "GET|HEAD",
        "uri": "admin\/delete_help\/{id}",
        "name": null,
        "action": "App\\Http\\Controllers\\Admin\\HelpController@delete",
        "middleware": "web,admin_guest,admin_can:manage_help"
    }, {
        "domain": null,
        "method": "GET|HEAD",
        "uri": "admin\/delete_help_category\/{id}",
        "name": null,
        "action": "App\\Http\\Controllers\\Admin\\HelpCategoryController@delete",
        "middleware": "web,admin_guest,admin_can:manage_help"
    }, {
        "domain": null,
        "method": "GET|HEAD",
        "uri": "admin\/delete_help_subcategory\/{id}",
        "name": null,
        "action": "App\\Http\\Controllers\\Admin\\HelpSubCategoryController@delete",
        "middleware": "web,admin_guest,admin_can:manage_help"
    }, {
        "domain": null,
        "method": "GET|HEAD",
        "uri": "admin\/delete_language\/{id}",
        "name": null,
        "action": "App\\Http\\Controllers\\Admin\\LanguageController@delete",
        "middleware": "web,admin_guest,admin_can:manage_language"
    }, {
        "domain": null,
        "method": "GET|HEAD",
        "uri": "admin\/delete_location\/{id}",
        "name": null,
        "action": "App\\Http\\Controllers\\Admin\\LocationsController@delete",
        "middleware": "web,admin_guest,admin_can:manage_locations"
    }, {
        "domain": null,
        "method": "GET|HEAD",
        "uri": "admin\/delete_manage_fare\/{id}",
        "name": null,
        "action": "App\\Http\\Controllers\\Admin\\ManageFareController@delete",
        "middleware": "web,admin_guest,admin_can:manage_peak_based_fare"
    }, {
        "domain": null,
        "method": "GET|HEAD",
        "uri": "admin\/delete_page\/{id}",
        "name": null,
        "action": "App\\Http\\Controllers\\Admin\\PagesController@delete",
        "middleware": "web,admin_guest,admin_can:manage_static_pages"
    }, {
        "domain": null,
        "method": "GET|HEAD",
        "uri": "admin\/delete_promo_code\/{id}",
        "name": null,
        "action": "App\\Http\\Controllers\\Admin\\PromocodeController@delete",
        "middleware": "web,admin_guest,admin_can:manage_promo_code"
    }, {
        "domain": null,
        "method": "GET|HEAD",
        "uri": "admin\/delete_rating\/{id}",
        "name": null,
        "action": "App\\Http\\Controllers\\Admin\\RatingController@delete",
        "middleware": "web,admin_guest,admin_can:manage_rating"
    }, {
        "domain": null,
        "method": "GET|POST|HEAD",
        "uri": "admin\/delete_rider\/{id}",
        "name": null,
        "action": "App\\Http\\Controllers\\Admin\\RiderController@delete",
        "middleware": "web,admin_guest,admin_can:delete_rider"
    }, {
        "domain": null,
        "method": "GET|HEAD",
        "uri": "admin\/delete_role\/{id}",
        "name": null,
        "action": "App\\Http\\Controllers\\Admin\\RolesController@delete",
        "middleware": "web,admin_guest,admin_can:manage_admin"
    }, {
        "domain": null,
        "method": "GET|POST|HEAD",
        "uri": "admin\/delete_vehicle\/{id}",
        "name": null,
        "action": "App\\Http\\Controllers\\Admin\\VehicleController@delete",
        "middleware": "web,admin_guest,admin_can:manage_vehicle"
    }, {
        "domain": null,
        "method": "GET|HEAD",
        "uri": "admin\/delete_wallet\/{id}",
        "name": null,
        "action": "App\\Http\\Controllers\\Admin\\WalletController@delete",
        "middleware": "web,admin_guest,admin_can:manage_wallet"
    }, {
        "domain": null,
        "method": "GET|HEAD",
        "uri": "admin\/detail_request\/{id}",
        "name": null,
        "action": "App\\Http\\Controllers\\Admin\\RequestController@detail_request",
        "middleware": "web,admin_guest,admin_can:manage_requests"
    }, {
        "domain": null,
        "method": "GET|HEAD",
        "uri": "admin\/details\/{type}",
        "name": "owe_details",
        "action": "App\\Http\\Controllers\\Admin\\OweController@owe_details",
        "middleware": "web,admin_guest,admin_can:manage_owe_amount"
    }, {
        "domain": null,
        "method": "GET|HEAD",
        "uri": "admin\/driver",
        "name": null,
        "action": "App\\Http\\Controllers\\Admin\\DriverController@index",
        "middleware": "web,admin_guest,admin_can:view_driver"
    }, {
        "domain": null,
        "method": "POST",
        "uri": "admin\/driver_list",
        "name": null,
        "action": "App\\Http\\Controllers\\Admin\\ManualBookingController@driver_list",
        "middleware": "web,admin_guest,admin_can:manage_manual_booking"
    }, {
        "domain": null,
        "method": "GET|HEAD",
        "uri": "admin\/driver_payment",
        "name": "driver_payment",
        "action": "App\\Http\\Controllers\\Admin\\OweController@driver_payment",
        "middleware": "web,admin_guest"
    }, {
        "domain": null,
        "method": "GET|HEAD",
        "uri": "admin\/driver_statement",
        "name": null,
        "action": "App\\Http\\Controllers\\Admin\\StatementController@driver_statement",
        "middleware": "web,admin_guest,admin_can:manage_statements"
    }, {
        "domain": null,
        "method": "GET|POST|HEAD",
        "uri": "admin\/edit_admin_users\/{id}",
        "name": null,
        "action": "App\\Http\\Controllers\\Admin\\AdminController@update",
        "middleware": "web,admin_guest,admin_can:manage_admin"
    }, {
        "domain": null,
        "method": "GET|POST|HEAD",
        "uri": "admin\/edit_car_type\/{id}",
        "name": null,
        "action": "App\\Http\\Controllers\\Admin\\CarTypeController@update",
        "middleware": "web,admin_guest,admin_can:manage_car_type"
    }, {
        "domain": null,
        "method": "GET|POST|HEAD",
        "uri": "admin\/edit_company\/{id}",
        "name": null,
        "action": "App\\Http\\Controllers\\Admin\\CompanyController@update",
        "middleware": "web,admin_guest,admin_can:edit_company"
    }, {
        "domain": null,
        "method": "GET|POST|HEAD",
        "uri": "admin\/edit_country\/{id}",
        "name": null,
        "action": "App\\Http\\Controllers\\Admin\\CountryController@update",
        "middleware": "web,admin_guest,admin_can:manage_country"
    }, {
        "domain": null,
        "method": "GET|POST|HEAD",
        "uri": "admin\/edit_currency\/{id}",
        "name": null,
        "action": "App\\Http\\Controllers\\Admin\\CurrencyController@update",
        "middleware": "web,admin_guest,admin_can:manage_currency"
    }, {
        "domain": null,
        "method": "GET|POST|HEAD",
        "uri": "admin\/edit_driver\/{id}",
        "name": null,
        "action": "App\\Http\\Controllers\\Admin\\DriverController@update",
        "middleware": "web,admin_guest,admin_can:edit_driver"
    }, {
        "domain": null,
        "method": "GET|POST|HEAD",
        "uri": "admin\/edit_help\/{id}",
        "name": null,
        "action": "App\\Http\\Controllers\\Admin\\HelpController@update",
        "middleware": "web,admin_guest,admin_can:manage_help"
    }, {
        "domain": null,
        "method": "GET|POST|HEAD",
        "uri": "admin\/edit_help_category\/{id}",
        "name": null,
        "action": "App\\Http\\Controllers\\Admin\\HelpCategoryController@update",
        "middleware": "web,admin_guest,admin_can:manage_help"
    }, {
        "domain": null,
        "method": "GET|POST|HEAD",
        "uri": "admin\/edit_help_subcategory\/{id}",
        "name": null,
        "action": "App\\Http\\Controllers\\Admin\\HelpSubCategoryController@update",
        "middleware": "web,admin_guest,admin_can:manage_help"
    }, {
        "domain": null,
        "method": "GET|POST|HEAD",
        "uri": "admin\/edit_language\/{id}",
        "name": null,
        "action": "App\\Http\\Controllers\\Admin\\LanguageController@update",
        "middleware": "web,admin_guest,admin_can:manage_language"
    }, {
        "domain": null,
        "method": "GET|POST|HEAD",
        "uri": "admin\/edit_location\/{id}",
        "name": null,
        "action": "App\\Http\\Controllers\\Admin\\LocationsController@update",
        "middleware": "web,admin_guest,admin_can:manage_locations"
    }, {
        "domain": null,
        "method": "GET|POST|HEAD",
        "uri": "admin\/edit_manage_fare\/{id}",
        "name": null,
        "action": "App\\Http\\Controllers\\Admin\\ManageFareController@update",
        "middleware": "web,admin_guest,admin_can:manage_peak_based_fare"
    }, {
        "domain": null,
        "method": "GET|POST|HEAD",
        "uri": "admin\/edit_meta\/{id}",
        "name": null,
        "action": "App\\Http\\Controllers\\Admin\\MetasController@update",
        "middleware": "web,admin_guest,admin_can:manage_metas"
    }, {
        "domain": null,
        "method": "GET|POST|HEAD",
        "uri": "admin\/edit_page\/{id}",
        "name": null,
        "action": "App\\Http\\Controllers\\Admin\\PagesController@update",
        "middleware": "web,admin_guest,admin_can:manage_static_pages"
    }, {
        "domain": null,
        "method": "GET|POST|HEAD",
        "uri": "admin\/edit_promo_code\/{id}",
        "name": null,
        "action": "App\\Http\\Controllers\\Admin\\PromocodeController@update",
        "middleware": "web,admin_guest,admin_can:manage_promo_code"
    }, {
        "domain": null,
        "method": "GET|POST|HEAD",
        "uri": "admin\/edit_rider\/{id}",
        "name": null,
        "action": "App\\Http\\Controllers\\Admin\\RiderController@update",
        "middleware": "web,admin_guest,admin_can:edit_rider"
    }, {
        "domain": null,
        "method": "GET|POST|HEAD",
        "uri": "admin\/edit_role\/{id}",
        "name": null,
        "action": "App\\Http\\Controllers\\Admin\\RolesController@update",
        "middleware": "web,admin_guest,admin_can:manage_admin"
    }, {
        "domain": null,
        "method": "GET|POST|HEAD",
        "uri": "admin\/edit_vehicle\/{id}",
        "name": null,
        "action": "App\\Http\\Controllers\\Admin\\VehicleController@update",
        "middleware": "web,admin_guest,admin_can:manage_vehicle"
    }, {
        "domain": null,
        "method": "GET|POST|HEAD",
        "uri": "admin\/edit_wallet\/{id}",
        "name": null,
        "action": "App\\Http\\Controllers\\Admin\\WalletController@update",
        "middleware": "web,admin_guest,admin_can:manage_wallet"
    }, {
        "domain": null,
        "method": "GET|POST|HEAD",
        "uri": "admin\/email_settings",
        "name": null,
        "action": "App\\Http\\Controllers\\Admin\\EmailController@index",
        "middleware": "web,admin_guest,admin_can:email_settings"
    }, {
        "domain": null,
        "method": "GET|POST|HEAD",
        "uri": "admin\/fees",
        "name": null,
        "action": "App\\Http\\Controllers\\Admin\\FeesController@index",
        "middleware": "web,admin_guest,admin_can:manage_fees"
    }, {
        "domain": null,
        "method": "POST",
        "uri": "admin\/get_driver",
        "name": null,
        "action": "App\\Http\\Controllers\\Admin\\ManualBookingController@get_driver",
        "middleware": "web,admin_guest,admin_can:manage_manual_booking"
    }, {
        "domain": null,
        "method": "POST",
        "uri": "admin\/get_send_users",
        "name": null,
        "action": "App\\Http\\Controllers\\Admin\\SendmessageController@get_send_users",
        "middleware": "web,admin_guest,admin_can:manage_send_message"
    }, {
        "domain": null,
        "method": "POST",
        "uri": "admin\/get_statement_counts",
        "name": null,
        "action": "App\\Http\\Controllers\\Admin\\StatementController@get_statement_counts",
        "middleware": "web,admin_guest,admin_can:manage_statements"
    }, {
        "domain": null,
        "method": "GET|POST|HEAD",
        "uri": "admin\/heat-map",
        "name": null,
        "action": "App\\Http\\Controllers\\Admin\\MapController@heat_map",
        "middleware": "web,admin_guest,admin_can:manage_heat_map"
    }, {
        "domain": null,
        "method": "GET|POST|HEAD",
        "uri": "admin\/heat-map-data",
        "name": null,
        "action": "App\\Http\\Controllers\\Admin\\MapController@heat_map_data",
        "middleware": "web,admin_guest,admin_can:manage_heat_map"
    }, {
        "domain": null,
        "method": "GET|HEAD",
        "uri": "admin\/help",
        "name": null,
        "action": "App\\Http\\Controllers\\Admin\\HelpController@index",
        "middleware": "web,admin_guest,admin_can:manage_help"
    }, {
        "domain": null,
        "method": "GET|HEAD",
        "uri": "admin\/help_category",
        "name": null,
        "action": "App\\Http\\Controllers\\Admin\\HelpCategoryController@index",
        "middleware": "web,admin_guest,admin_can:manage_help"
    }, {
        "domain": null,
        "method": "GET|HEAD",
        "uri": "admin\/help_subcategory",
        "name": null,
        "action": "App\\Http\\Controllers\\Admin\\HelpSubCategoryController@index",
        "middleware": "web,admin_guest,admin_can:manage_help"
    }, {
        "domain": null,
        "method": "POST",
        "uri": "admin\/immediate_request",
        "name": null,
        "action": "App\\Http\\Controllers\\Admin\\LaterBookingController@immediate_request",
        "middleware": "web,admin_guest,admin_can:manage_manual_booking"
    }, {
        "domain": null,
        "method": "GET|POST|HEAD",
        "uri": "admin\/join_us",
        "name": null,
        "action": "App\\Http\\Controllers\\Admin\\JoinUsController@index",
        "middleware": "web,admin_guest,admin_can:manage_join_us"
    }, {
        "domain": null,
        "method": "GET|HEAD",
        "uri": "admin\/language",
        "name": null,
        "action": "App\\Http\\Controllers\\Admin\\LanguageController@index",
        "middleware": "web,admin_guest,admin_can:manage_language"
    }, {
        "domain": null,
        "method": "GET|HEAD",
        "uri": "admin\/later_booking",
        "name": null,
        "action": "App\\Http\\Controllers\\Admin\\LaterBookingController@index",
        "middleware": "web,admin_guest,admin_can:manage_manual_booking"
    }, {
        "domain": null,
        "method": "GET|HEAD",
        "uri": "admin\/locations",
        "name": null,
        "action": "App\\Http\\Controllers\\Admin\\LocationsController@index",
        "middleware": "web,admin_guest,admin_can:manage_locations"
    }, {
        "domain": null,
        "method": "GET|HEAD",
        "uri": "admin\/login",
        "name": null,
        "action": "App\\Http\\Controllers\\Admin\\AdminController@login",
        "middleware": "web,admin_auth"
    }, {
        "domain": null,
        "method": "GET|HEAD",
        "uri": "admin\/logout",
        "name": null,
        "action": "App\\Http\\Controllers\\Admin\\AdminController@logout",
        "middleware": "web,admin_guest"
    }, {
        "domain": null,
        "method": "POST",
        "uri": "admin\/make_payout",
        "name": null,
        "action": "App\\Http\\Controllers\\Admin\\PayoutController@payout_to_driver",
        "middleware": "web,admin_guest,admin_can:manage_driver_payments"
    }, {
        "domain": null,
        "method": "POST",
        "uri": "admin\/make_payout\/company",
        "name": null,
        "action": "App\\Http\\Controllers\\Admin\\CompanyPayoutController@payout_to_company",
        "middleware": "web,admin_guest,admin_can:manage_company_payment"
    }, {
        "domain": null,
        "method": "GET|HEAD",
        "uri": "admin\/manage_fare",
        "name": null,
        "action": "App\\Http\\Controllers\\Admin\\ManageFareController@index",
        "middleware": "web,admin_guest,admin_can:manage_peak_based_fare"
    }, {
        "domain": null,
        "method": "POST",
        "uri": "admin\/manage_vehicle\/{company_id}\/get_driver",
        "name": null,
        "action": "App\\Http\\Controllers\\Admin\\VehicleController@get_driver",
        "middleware": "web,admin_guest,admin_can:manage_vehicle"
    }, {
        "domain": null,
        "method": "POST",
        "uri": "admin\/manual_booking\/cancel",
        "name": null,
        "action": "App\\Http\\Controllers\\Admin\\LaterBookingController@cancel",
        "middleware": "web,admin_guest,admin_can:manage_manual_booking"
    }, {
        "domain": null,
        "method": "POST",
        "uri": "admin\/manual_booking\/store",
        "name": null,
        "action": "App\\Http\\Controllers\\Admin\\ManualBookingController@store",
        "middleware": "web,admin_guest,admin_can:manage_manual_booking"
    }, {
        "domain": null,
        "method": "GET|HEAD",
        "uri": "admin\/manual_booking\/{id?}",
        "name": null,
        "action": "App\\Http\\Controllers\\Admin\\ManualBookingController@index",
        "middleware": "web,admin_guest,admin_can:manage_manual_booking"
    }, {
        "domain": null,
        "method": "GET|POST|HEAD",
        "uri": "admin\/map",
        "name": null,
        "action": "App\\Http\\Controllers\\Admin\\MapController@index",
        "middleware": "web,admin_guest,admin_can:manage_map"
    }, {
        "domain": null,
        "method": "GET|POST|HEAD",
        "uri": "admin\/mapdata",
        "name": null,
        "action": "App\\Http\\Controllers\\Admin\\MapController@mapdata",
        "middleware": "web,admin_guest,admin_can:manage_map"
    }, {
        "domain": null,
        "method": "GET|POST|HEAD",
        "uri": "admin\/metas",
        "name": null,
        "action": "App\\Http\\Controllers\\Admin\\MetasController@index",
        "middleware": "web,admin_guest,admin_can:manage_metas"
    }, {
        "domain": null,
        "method": "GET|POST|HEAD",
        "uri": "admin\/owe",
        "name": "owe",
        "action": "App\\Http\\Controllers\\Admin\\OweController@index",
        "middleware": "web,admin_guest,admin_can:manage_owe_amount"
    }, {
        "domain": null,
        "method": "GET|HEAD",
        "uri": "admin\/pages",
        "name": null,
        "action": "App\\Http\\Controllers\\Admin\\PagesController@index",
        "middleware": "web,admin_guest,admin_can:manage_static_pages"
    }, {
        "domain": null,
        "method": "GET|POST|HEAD",
        "uri": "admin\/payment_gateway",
        "name": null,
        "action": "App\\Http\\Controllers\\Admin\\PaymentGatewayController@index",
        "middleware": "web,admin_guest,admin_can:manage_payment_gateway"
    }, {
        "domain": null,
        "method": "GET|POST|HEAD",
        "uri": "admin\/payments",
        "name": null,
        "action": "App\\Http\\Controllers\\Admin\\PaymentsController@index",
        "middleware": "web,admin_guest,admin_can:manage_payments"
    }, {
        "domain": null,
        "method": "GET|HEAD",
        "uri": "admin\/payments\/export\/{from}\/{to}",
        "name": null,
        "action": "App\\Http\\Controllers\\Admin\\PaymentsController@export",
        "middleware": "web,admin_guest,admin_can:manage_payments"
    }, {
        "domain": null,
        "method": "GET|HEAD",
        "uri": "admin\/payout\/company\/overall",
        "name": null,
        "action": "App\\Http\\Controllers\\Admin\\CompanyPayoutController@overall_payout",
        "middleware": "web,admin_guest,admin_can:manage_company_payment"
    }, {
        "domain": null,
        "method": "GET|HEAD",
        "uri": "admin\/payout\/overall",
        "name": null,
        "action": "App\\Http\\Controllers\\Admin\\PayoutController@overall_payout",
        "middleware": "web,admin_guest,admin_can:manage_driver_payments"
    }, {
        "domain": null,
        "method": "GET|HEAD",
        "uri": "admin\/per_day_report\/company\/{company_id}\/{date}",
        "name": null,
        "action": "App\\Http\\Controllers\\Admin\\CompanyPayoutController@payout_per_day_report",
        "middleware": "web,admin_guest,admin_can:manage_company_payment"
    }, {
        "domain": null,
        "method": "GET|HEAD",
        "uri": "admin\/per_day_report\/{driver_id}\/{date}",
        "name": null,
        "action": "App\\Http\\Controllers\\Admin\\PayoutController@payout_per_day_report",
        "middleware": "web,admin_guest,admin_can:manage_driver_payments"
    }, {
        "domain": null,
        "method": "GET|HEAD",
        "uri": "admin\/per_week_report\/company\/{company_id}\/{start_date}\/{end_date}",
        "name": null,
        "action": "App\\Http\\Controllers\\Admin\\CompanyPayoutController@payout_per_week_report",
        "middleware": "web,admin_guest,admin_can:manage_company_payment"
    }, {
        "domain": null,
        "method": "GET|HEAD",
        "uri": "admin\/per_week_report\/{driver_id}\/{start_date}\/{end_date}",
        "name": null,
        "action": "App\\Http\\Controllers\\Admin\\PayoutController@payout_per_week_report",
        "middleware": "web,admin_guest,admin_can:manage_driver_payments"
    }, {
        "domain": null,
        "method": "GET|HEAD",
        "uri": "admin\/promo_code",
        "name": null,
        "action": "App\\Http\\Controllers\\Admin\\PromocodeController@index",
        "middleware": "web,admin_guest,admin_can:manage_promo_code"
    }, {
        "domain": null,
        "method": "GET|HEAD",
        "uri": "admin\/rating",
        "name": null,
        "action": "App\\Http\\Controllers\\Admin\\RatingController@index",
        "middleware": "web,admin_guest,admin_can:manage_rating"
    }, {
        "domain": null,
        "method": "GET|POST|HEAD",
        "uri": "admin\/request",
        "name": null,
        "action": "App\\Http\\Controllers\\Admin\\RequestController@index",
        "middleware": "web,admin_guest,admin_can:manage_requests"
    }, {
        "domain": null,
        "method": "GET|HEAD",
        "uri": "admin\/rider",
        "name": null,
        "action": "App\\Http\\Controllers\\Admin\\RiderController@index",
        "middleware": "web,admin_guest,admin_can:view_rider"
    }, {
        "domain": null,
        "method": "GET|HEAD",
        "uri": "admin\/roles",
        "name": null,
        "action": "App\\Http\\Controllers\\Admin\\RolesController@index",
        "middleware": "web,admin_guest,admin_can:manage_admin"
    }, {
        "domain": null,
        "method": "POST",
        "uri": "admin\/search_cars",
        "name": null,
        "action": "App\\Http\\Controllers\\Admin\\ManualBookingController@search_cars",
        "middleware": "web,admin_guest,admin_can:manage_manual_booking"
    }, {
        "domain": null,
        "method": "POST",
        "uri": "admin\/search_phone",
        "name": null,
        "action": "App\\Http\\Controllers\\Admin\\ManualBookingController@search_phone",
        "middleware": "web,admin_guest,admin_can:manage_manual_booking"
    }, {
        "domain": null,
        "method": "GET|POST|HEAD",
        "uri": "admin\/send_email",
        "name": null,
        "action": "App\\Http\\Controllers\\Admin\\EmailController@send_email",
        "middleware": "web,admin_guest,admin_can:send_email"
    }, {
        "domain": null,
        "method": "GET|POST|HEAD",
        "uri": "admin\/send_message",
        "name": null,
        "action": "App\\Http\\Controllers\\Admin\\SendmessageController@index",
        "middleware": "web,admin_guest,admin_can:manage_send_message"
    }, {
        "domain": null,
        "method": "GET|POST|HEAD",
        "uri": "admin\/site_setting",
        "name": null,
        "action": "App\\Http\\Controllers\\Admin\\SiteSettingsController@index",
        "middleware": "web,admin_guest,admin_can:manage_site_settings"
    }, {
        "domain": null,
        "method": "GET|HEAD",
        "uri": "admin\/statement_all",
        "name": null,
        "action": "App\\Http\\Controllers\\Admin\\StatementController@custom_statement",
        "middleware": "web,admin_guest,admin_can:manage_statements"
    }, {
        "domain": null,
        "method": "GET|HEAD",
        "uri": "admin\/statements\/{type}",
        "name": null,
        "action": "App\\Http\\Controllers\\Admin\\StatementController@index",
        "middleware": "web,admin_guest,admin_can:manage_statements"
    }, {
        "domain": null,
        "method": "GET|POST|HEAD",
        "uri": "admin\/trips",
        "name": null,
        "action": "App\\Http\\Controllers\\Admin\\TripsController@index",
        "middleware": "web,admin_guest,admin_can:manage_trips"
    }, {
        "domain": null,
        "method": "GET|HEAD",
        "uri": "admin\/trips\/export\/{from}\/{to}",
        "name": null,
        "action": "App\\Http\\Controllers\\Admin\\TripsController@export",
        "middleware": "web,admin_guest,admin_can:manage_trips"
    }, {
        "domain": null,
        "method": "POST",
        "uri": "admin\/trips\/payout\/{id}",
        "name": null,
        "action": "App\\Http\\Controllers\\Admin\\TripsController@payout",
        "middleware": "web,admin_guest,admin_can:manage_trips"
    }, {
        "domain": null,
        "method": "GET|HEAD",
        "uri": "admin\/update_driver_payment",
        "name": "update_payment",
        "action": "App\\Http\\Controllers\\Admin\\OweController@update_payment",
        "middleware": "web,admin_guest,admin_can:manage_owe_amount"
    }, {
        "domain": null,
        "method": "GET|HEAD",
        "uri": "admin\/vehicle",
        "name": null,
        "action": "App\\Http\\Controllers\\Admin\\VehicleController@index",
        "middleware": "web,admin_guest,admin_can:manage_vehicle"
    }, {
        "domain": null,
        "method": "GET|HEAD",
        "uri": "admin\/view_driver_statement\/{driver_id}",
        "name": null,
        "action": "App\\Http\\Controllers\\Admin\\StatementController@view_driver_statement",
        "middleware": "web,admin_guest,admin_can:manage_statements"
    }, {
        "domain": null,
        "method": "GET|HEAD",
        "uri": "admin\/view_payments\/{id}",
        "name": null,
        "action": "App\\Http\\Controllers\\Admin\\PaymentsController@view",
        "middleware": "web,admin_guest,admin_can:manage_payments"
    }, {
        "domain": null,
        "method": "GET|HEAD",
        "uri": "admin\/view_trips\/{id}",
        "name": null,
        "action": "App\\Http\\Controllers\\Admin\\TripsController@view",
        "middleware": "web,admin_guest,admin_can:manage_trips"
    }, {
        "domain": null,
        "method": "GET|POST|HEAD",
        "uri": "admin\/wallet",
        "name": null,
        "action": "App\\Http\\Controllers\\Admin\\WalletController@index",
        "middleware": "web,admin_guest,admin_can:manage_wallet"
    }, {
        "domain": null,
        "method": "GET|HEAD",
        "uri": "admin\/weekly_payout\/company\/{company_id}",
        "name": null,
        "action": "App\\Http\\Controllers\\Admin\\CompanyPayoutController@weekly_payout",
        "middleware": "web,admin_guest,admin_can:manage_company_payment"
    }, {
        "domain": null,
        "method": "GET|HEAD",
        "uri": "admin\/weekly_payout\/{driver_id}",
        "name": null,
        "action": "App\\Http\\Controllers\\Admin\\PayoutController@weekly_payout",
        "middleware": "web,admin_guest,admin_can:manage_driver_payments"
    }, {
        "domain": null,
        "method": "GET|HEAD",
        "uri": "ajax_help_search",
        "name": null,
        "action": "App\\Http\\Controllers\\HomeController@ajax_help_search",
        "middleware": "web,locale"
    }, {
        "domain": null,
        "method": "POST",
        "uri": "ajax_payment",
        "name": null,
        "action": "App\\Http\\Controllers\\DriverDashboardController@ajax_payment",
        "middleware": "web,locale,driver_guest"
    }, {
        "domain": null,
        "method": "POST",
        "uri": "ajax_trips\/{id}",
        "name": null,
        "action": "App\\Http\\Controllers\\DashboardController@ajax_trips",
        "middleware": "web,locale"
    }, {
        "domain": null,
        "method": "POST",
        "uri": "api\/Asking-for-rest-link",
        "name": null,
        "action": "App\\Http\\Controllers\\Api\\ProfileController@sendResetMyPassword",
        "middleware": "api,jwt.auth"
    }, {
        "domain": null,
        "method": "POST",
        "uri": "api\/add-card-details",
        "name": null,
        "action": "App\\Http\\Controllers\\Api\\ProfileController@add_card_details",
        "middleware": "api,jwt.auth"
    }, {
        "domain": null,
        "method": "POST",
        "uri": "api\/add-payout",
        "name": null,
        "action": "App\\Http\\Controllers\\Api\\EarningController@add_payout",
        "middleware": "api,jwt.auth"
    }, {
        "domain": null,
        "method": "POST",
        "uri": "api\/add-payout-preference",
        "name": null,
        "action": "App\\Http\\Controllers\\Api\\DriverController@add_payout_preference",
        "middleware": "api,jwt.auth"
    }, {
        "domain": null,
        "method": "POST",
        "uri": "api\/add-promo-code",
        "name": null,
        "action": "App\\Http\\Controllers\\Api\\EarningController@add_promo_code",
        "middleware": "api,jwt.auth"
    }, {
        "domain": null,
        "method": "POST",
        "uri": "api\/add-wallet",
        "name": null,
        "action": "App\\Http\\Controllers\\Api\\EarningController@add_wallet",
        "middleware": "api,jwt.auth"
    }, {
        "domain": null,
        "method": "POST",
        "uri": "api\/after_payment",
        "name": null,
        "action": "App\\Http\\Controllers\\Api\\EarningController@after_payment",
        "middleware": "api,jwt.auth"
    }, {
        "domain": null,
        "method": "POST",
        "uri": "api\/arrive-now",
        "name": null,
        "action": "App\\Http\\Controllers\\Api\\TripController@arive_now",
        "middleware": "api,jwt.auth"
    }, {
        "domain": null,
        "method": "POST",
        "uri": "api\/authenticate-to-get-token",
        "name": null,
        "action": "App\\Http\\Controllers\\Api\\TokenAuthController@authenticate",
        "middleware": "api"
    }, {
        "domain": null,
        "method": "POST",
        "uri": "api\/authenticate\/user",
        "name": null,
        "action": "App\\Http\\Controllers\\Api\\TokenAuthController@getAuthenticatedUser",
        "middleware": "api,jwt.auth"
    }, {
        "domain": null,
        "method": "POST",
        "uri": "api\/begin-trip",
        "name": null,
        "action": "App\\Http\\Controllers\\Api\\TripController@begin_trip",
        "middleware": "api,jwt.auth"
    }, {
        "domain": null,
        "method": "POST",
        "uri": "api\/cancel-trip",
        "name": null,
        "action": "App\\Http\\Controllers\\Api\\TripController@cancel_trip",
        "middleware": "api,jwt.auth"
    }, {
        "domain": null,
        "method": "GET|HEAD",
        "uri": "api\/check_version",
        "name": null,
        "action": "App\\Http\\Controllers\\Api\\RiderController@check_version",
        "middleware": "api,jwt.auth"
    }, {
        "domain": null,
        "method": "GET|HEAD",
        "uri": "api\/cron_request_car",
        "name": null,
        "action": "App\\Http\\Controllers\\Api\\RiderController@cron_request_car",
        "middleware": "api,jwt.auth"
    }, {
        "domain": null,
        "method": "GET|HEAD",
        "uri": "api\/currency-list",
        "name": null,
        "action": "App\\Http\\Controllers\\Api\\TokenAuthController@currency_list",
        "middleware": "api"
    }, {
        "domain": null,
        "method": "POST",
        "uri": "api\/device-update",
        "name": null,
        "action": "App\\Http\\Controllers\\Api\\TokenAuthController@update_device",
        "middleware": "api,jwt.auth"
    }, {
        "domain": null,
        "method": "POST",
        "uri": "api\/document-upload",
        "name": null,
        "action": "App\\Http\\Controllers\\Api\\ProfileController@document_upload",
        "middleware": "api,jwt.auth"
    }, {
        "domain": null,
        "method": "POST",
        "uri": "api\/driver-accept-request",
        "name": null,
        "action": "App\\Http\\Controllers\\Api\\DriverController@accept_request",
        "middleware": "api,jwt.auth"
    }, {
        "domain": null,
        "method": "POST",
        "uri": "api\/driver-bank-details",
        "name": null,
        "action": "App\\Http\\Controllers\\Api\\DriverController@driver_bank_details",
        "middleware": "api,jwt.auth"
    }, {
        "domain": null,
        "method": "POST",
        "uri": "api\/driver-cash-collected",
        "name": null,
        "action": "App\\Http\\Controllers\\Api\\DriverController@cash_collected",
        "middleware": "api,jwt.auth"
    }, {
        "domain": null,
        "method": "POST",
        "uri": "api\/driver-check-status",
        "name": null,
        "action": "App\\Http\\Controllers\\Api\\DriverController@check_status",
        "middleware": "api,jwt.auth"
    }, {
        "domain": null,
        "method": "GET|HEAD",
        "uri": "api\/driver-country-list",
        "name": null,
        "action": "App\\Http\\Controllers\\Api\\DriverController@country_list",
        "middleware": "api,jwt.auth"
    }, {
        "domain": null,
        "method": "POST",
        "uri": "api\/driver-details",
        "name": null,
        "action": "App\\Http\\Controllers\\Api\\RiderController@driver_details",
        "middleware": "api,jwt.auth"
    }, {
        "domain": null,
        "method": "POST",
        "uri": "api\/driver-payout-changes",
        "name": null,
        "action": "App\\Http\\Controllers\\Api\\DriverController@payout_changes",
        "middleware": "api,jwt.auth"
    }, {
        "domain": null,
        "method": "GET|HEAD",
        "uri": "api\/driver-payout-details",
        "name": null,
        "action": "App\\Http\\Controllers\\Api\\DriverController@payout_details",
        "middleware": "api,jwt.auth"
    }, {
        "domain": null,
        "method": "POST",
        "uri": "api\/driver-rating",
        "name": null,
        "action": "App\\Http\\Controllers\\Api\\RatingController@driver_rating",
        "middleware": "api,jwt.auth"
    }, {
        "domain": null,
        "method": "GET|HEAD",
        "uri": "api\/driver-stripe-supported-country-list",
        "name": null,
        "action": "App\\Http\\Controllers\\Api\\DriverController@stripe_supported_country_list",
        "middleware": "api,jwt.auth"
    }, {
        "domain": null,
        "method": "POST",
        "uri": "api\/driver-trips-history",
        "name": null,
        "action": "App\\Http\\Controllers\\Api\\TripController@driver_trips_history",
        "middleware": "api,jwt.auth"
    }, {
        "domain": null,
        "method": "POST",
        "uri": "api\/driver-update-location",
        "name": null,
        "action": "App\\Http\\Controllers\\Api\\DriverController@updatelocation",
        "middleware": "api,jwt.auth"
    }, {
        "domain": null,
        "method": "POST",
        "uri": "api\/earning-chart",
        "name": null,
        "action": "App\\Http\\Controllers\\Api\\EarningController@earning_chart",
        "middleware": "api,jwt.auth"
    }, {
        "domain": null,
        "method": "POST",
        "uri": "api\/emailvalidation",
        "name": null,
        "action": "App\\Http\\Controllers\\Api\\TokenAuthController@emailvalidation",
        "middleware": "api"
    }, {
        "domain": null,
        "method": "POST",
        "uri": "api\/end-trip",
        "name": null,
        "action": "App\\Http\\Controllers\\Api\\TripController@end_trip",
        "middleware": "api,jwt.auth"
    }, {
        "domain": null,
        "method": "POST",
        "uri": "api\/forgotpassword",
        "name": null,
        "action": "App\\Http\\Controllers\\Api\\TokenAuthController@forgotpassword",
        "middleware": "api"
    }, {
        "domain": null,
        "method": "POST",
        "uri": "api\/get-card-details",
        "name": null,
        "action": "App\\Http\\Controllers\\Api\\ProfileController@get_card_details",
        "middleware": "api,jwt.auth"
    }, {
        "domain": null,
        "method": "POST",
        "uri": "api\/get-driver-profile",
        "name": null,
        "action": "App\\Http\\Controllers\\Api\\ProfileController@get_driver_profile",
        "middleware": "api,jwt.auth"
    }, {
        "domain": null,
        "method": "POST",
        "uri": "api\/get-invoice",
        "name": null,
        "action": "App\\Http\\Controllers\\Api\\RatingController@getinvoice",
        "middleware": "api,jwt.auth"
    }, {
        "domain": null,
        "method": "POST",
        "uri": "api\/get-rider-profile",
        "name": null,
        "action": "App\\Http\\Controllers\\Api\\ProfileController@get_rider_profile",
        "middleware": "api,jwt.auth"
    }, {
        "domain": null,
        "method": "POST",
        "uri": "api\/get-rider-trips",
        "name": null,
        "action": "App\\Http\\Controllers\\Api\\TripController@get_rider_trips",
        "middleware": "api,jwt.auth"
    }, {
        "domain": null,
        "method": "POST",
        "uri": "api\/get-schedule-rides",
        "name": null,
        "action": "App\\Http\\Controllers\\Api\\RiderController@get_schedule_rides",
        "middleware": "api,jwt.auth"
    }, {
        "domain": null,
        "method": "POST",
        "uri": "api\/incomplete-trip-details",
        "name": null,
        "action": "App\\Http\\Controllers\\Api\\TripController@incomplete_trips",
        "middleware": "api,jwt.auth"
    }, {
        "domain": null,
        "method": "POST",
        "uri": "api\/language-update",
        "name": null,
        "action": "App\\Http\\Controllers\\Api\\TokenAuthController@language",
        "middleware": "api,jwt.auth"
    }, {
        "domain": null,
        "method": "GET|HEAD",
        "uri": "api\/language_list",
        "name": null,
        "action": "App\\Http\\Controllers\\Api\\TokenAuthController@language_list",
        "middleware": "api"
    }, {
        "domain": null,
        "method": "POST",
        "uri": "api\/login",
        "name": null,
        "action": "App\\Http\\Controllers\\Api\\TokenAuthController@login",
        "middleware": "api"
    }, {
        "domain": null,
        "method": "GET|HEAD",
        "uri": "api\/logout",
        "name": null,
        "action": "App\\Http\\Controllers\\Api\\TokenAuthController@logout",
        "middleware": "api,jwt.auth"
    }, {
        "domain": null,
        "method": "POST",
        "uri": "api\/map-upload",
        "name": null,
        "action": "App\\Http\\Controllers\\Api\\TripController@map_upload",
        "middleware": "api,jwt.auth"
    }, {
        "domain": null,
        "method": "POST",
        "uri": "api\/numbervalidation",
        "name": null,
        "action": "App\\Http\\Controllers\\Api\\TokenAuthController@numbervalidation",
        "middleware": "api"
    }, {
        "domain": null,
        "method": "POST",
        "uri": "api\/paypal-currency-conversion",
        "name": null,
        "action": "App\\Http\\Controllers\\Api\\TokenAuthController@paypal_currency_conversion",
        "middleware": "api"
    }, {
        "domain": null,
        "method": "POST",
        "uri": "api\/promo-details",
        "name": null,
        "action": "App\\Http\\Controllers\\Api\\RiderController@promo_details",
        "middleware": "api,jwt.auth"
    }, {
        "domain": null,
        "method": "POST",
        "uri": "api\/refresh-token",
        "name": null,
        "action": "App\\Http\\Controllers\\Api\\TokenAuthController@token",
        "middleware": "api,jwt.auth"
    }, {
        "domain": null,
        "method": "POST",
        "uri": "api\/register",
        "name": null,
        "action": "App\\Http\\Controllers\\Api\\TokenAuthController@register",
        "middleware": "api"
    }, {
        "domain": null,
        "method": "POST",
        "uri": "api\/request-cars",
        "name": null,
        "action": "App\\Http\\Controllers\\Api\\RiderController@request_cars",
        "middleware": "api,jwt.auth"
    }, {
        "domain": null,
        "method": "POST",
        "uri": "api\/rest-password",
        "name": null,
        "action": "App\\Http\\Controllers\\Api\\ResetPasswordController@require_rest_link",
        "middleware": "api"
    }, {
        "domain": null,
        "method": "POST",
        "uri": "api\/rider-feedback",
        "name": null,
        "action": "App\\Http\\Controllers\\Api\\RatingController@rider_feedback",
        "middleware": "api,jwt.auth"
    }, {
        "domain": null,
        "method": "POST",
        "uri": "api\/save-schedule-ride",
        "name": null,
        "action": "App\\Http\\Controllers\\Api\\RiderController@save_schedule_ride",
        "middleware": "api,jwt.auth"
    }, {
        "domain": null,
        "method": "POST",
        "uri": "api\/schedule-ride-cancel",
        "name": null,
        "action": "App\\Http\\Controllers\\Api\\RiderController@schedule_ride_cancel",
        "middleware": "api,jwt.auth"
    }, {
        "domain": null,
        "method": "POST",
        "uri": "api\/search-cars",
        "name": null,
        "action": "App\\Http\\Controllers\\Api\\RiderController@search_cars",
        "middleware": "api,jwt.auth"
    }, {
        "domain": null,
        "method": "POST",
        "uri": "api\/socialsignup",
        "name": null,
        "action": "App\\Http\\Controllers\\Api\\TokenAuthController@socialsignup",
        "middleware": "api"
    }, {
        "domain": null,
        "method": "POST",
        "uri": "api\/sos",
        "name": null,
        "action": "App\\Http\\Controllers\\Api\\RiderController@sos",
        "middleware": "api,jwt.auth"
    }, {
        "domain": null,
        "method": "POST",
        "uri": "api\/sosalert",
        "name": null,
        "action": "App\\Http\\Controllers\\Api\\RiderController@sosalert",
        "middleware": "api,jwt.auth"
    }, {
        "domain": null,
        "method": "POST",
        "uri": "api\/track-driver",
        "name": null,
        "action": "App\\Http\\Controllers\\Api\\RiderController@track_driver",
        "middleware": "api,jwt.auth"
    }, {
        "domain": null,
        "method": "POST",
        "uri": "api\/trip-rating",
        "name": null,
        "action": "App\\Http\\Controllers\\Api\\RatingController@trip_rating",
        "middleware": "api,jwt.auth"
    }, {
        "domain": null,
        "method": "POST",
        "uri": "api\/update-driver-profile",
        "name": null,
        "action": "App\\Http\\Controllers\\Api\\ProfileController@update_driver_profile",
        "middleware": "api,jwt.auth"
    }, {
        "domain": null,
        "method": "POST",
        "uri": "api\/update-rider-location",
        "name": null,
        "action": "App\\Http\\Controllers\\Api\\RiderController@updateriderlocation",
        "middleware": "api,jwt.auth"
    }, {
        "domain": null,
        "method": "POST",
        "uri": "api\/update-rider-profile",
        "name": null,
        "action": "App\\Http\\Controllers\\Api\\ProfileController@update_rider_location",
        "middleware": "api,jwt.auth"
    }, {
        "domain": null,
        "method": "POST",
        "uri": "api\/update-user-currency",
        "name": null,
        "action": "App\\Http\\Controllers\\Api\\ProfileController@update_user_currency",
        "middleware": "api,jwt.auth"
    }, {
        "domain": null,
        "method": "POST",
        "uri": "api\/upload_profile_image",
        "name": null,
        "action": "App\\Http\\Controllers\\Api\\ProfileController@upload_profile_image",
        "middleware": "api,jwt.auth"
    }, {
        "domain": null,
        "method": "POST",
        "uri": "api\/vehicle-details",
        "name": null,
        "action": "App\\Http\\Controllers\\Api\\ProfileController@vehicle_details",
        "middleware": "api,jwt.auth"
    }, {
        "domain": null,
        "method": "GET|HEAD",
        "uri": "auth\/{provider}",
        "name": null,
        "action": "App\\Http\\Controllers\\Auth\\SocialController@redirectToProvider",
        "middleware": "web,locale"
    }, {
        "domain": null,
        "method": "GET|HEAD",
        "uri": "auth\/{provider}\/callback",
        "name": null,
        "action": "App\\Http\\Controllers\\Auth\\SocialController@handleProviderCallback",
        "middleware": "web,locale"
    }, {
        "domain": null,
        "method": "GET|HEAD",
        "uri": "call_again",
        "name": null,
        "action": "App\\Http\\Controllers\\Api\\RiderController@call_again",
        "middleware": "web"
    }, {
        "domain": null,
        "method": "GET|HEAD",
        "uri": "check_push",
        "name": null,
        "action": "App\\Http\\Controllers\\Api\\RiderController@check_push",
        "middleware": "web"
    }, {
        "domain": null,
        "method": "GET|POST|HEAD",
        "uri": "company\/reset_password",
        "name": null,
        "action": "App\\Http\\Controllers\\UserController@company_reset_password",
        "middleware": "web,locale"
    }, {
        "domain": null,
        "method": "POST",
        "uri": "company_register",
        "name": null,
        "action": "App\\Http\\Controllers\\UserController@company_register",
        "middleware": "web,locale"
    }, {
        "domain": null,
        "method": "GET|HEAD",
        "uri": "currency_cron",
        "name": null,
        "action": "App\\Http\\Controllers\\HomeController@currency_cron",
        "middleware": "web,canInstall,locale"
    }, {
        "domain": null,
        "method": "POST",
        "uri": "document_upload\/{id}",
        "name": null,
        "action": "App\\Http\\Controllers\\DriverDashboardController@document_upload",
        "middleware": "web,locale,driver_guest"
    }, {
        "domain": null,
        "method": "GET|HEAD",
        "uri": "documents\/{id}",
        "name": null,
        "action": "App\\Http\\Controllers\\DriverDashboardController@documents",
        "middleware": "web,locale,driver_guest"
    }, {
        "domain": null,
        "method": "GET|HEAD",
        "uri": "download_invoice\/{id}",
        "name": null,
        "action": "App\\Http\\Controllers\\DriverDashboardController@download_invoice",
        "middleware": "web,locale"
    }, {
        "domain": null,
        "method": "GET|HEAD",
        "uri": "download_rider_invoice\/{id}",
        "name": null,
        "action": "App\\Http\\Controllers\\DashboardController@download_rider_invoice",
        "middleware": "web,locale"
    }, {
        "domain": null,
        "method": "GET|HEAD",
        "uri": "drive",
        "name": null,
        "action": "App\\Http\\Controllers\\DriveController@drive",
        "middleware": "web,locale"
    }, {
        "domain": null,
        "method": "GET|HEAD",
        "uri": "drive_safety",
        "name": null,
        "action": "App\\Http\\Controllers\\DriveController@drive_safety",
        "middleware": "web,locale"
    }, {
        "domain": null,
        "method": "GET|HEAD",
        "uri": "driver_app",
        "name": null,
        "action": "App\\Http\\Controllers\\DriveController@driver_app",
        "middleware": "web,locale"
    }, {
        "domain": null,
        "method": "GET|HEAD",
        "uri": "driver_banking",
        "name": null,
        "action": "App\\Http\\Controllers\\DriverDashboardController@driver_banking",
        "middleware": "web,locale,driver_guest"
    }, {
        "domain": null,
        "method": "GET|HEAD",
        "uri": "driver_dashboard",
        "name": null,
        "action": "Closure",
        "middleware": "web,locale,driver_guest"
    }, {
        "domain": null,
        "method": "GET|HEAD",
        "uri": "driver_invoice",
        "name": null,
        "action": "App\\Http\\Controllers\\DriverDashboardController@show_invoice",
        "middleware": "web,locale,driver_guest"
    }, {
        "domain": null,
        "method": "GET|HEAD",
        "uri": "driver_invoice\/{id}",
        "name": null,
        "action": "App\\Http\\Controllers\\DriverDashboardController@driver_invoice",
        "middleware": "web,locale,driver_guest"
    }, {
        "domain": null,
        "method": "GET|HEAD",
        "uri": "driver_payment",
        "name": null,
        "action": "App\\Http\\Controllers\\DriverDashboardController@driver_payment",
        "middleware": "web,locale,driver_guest"
    }, {
        "domain": null,
        "method": "GET|HEAD",
        "uri": "driver_profile",
        "name": null,
        "action": "App\\Http\\Controllers\\DriverDashboardController@driver_profile",
        "middleware": "web,locale,driver_guest"
    }, {
        "domain": null,
        "method": "POST",
        "uri": "driver_register",
        "name": null,
        "action": "App\\Http\\Controllers\\UserController@driver_register",
        "middleware": "web,locale"
    }, {
        "domain": null,
        "method": "GET|HEAD",
        "uri": "driver_trip",
        "name": null,
        "action": "App\\Http\\Controllers\\DriverDashboardController@driver_trip",
        "middleware": "web,locale,driver_guest"
    }, {
        "domain": null,
        "method": "GET|HEAD",
        "uri": "driver_trip_detail\/{id}",
        "name": null,
        "action": "App\\Http\\Controllers\\DriverDashboardController@driver_trip_detail",
        "middleware": "web,locale,driver_guest"
    }, {
        "domain": null,
        "method": "POST",
        "uri": "driver_update_profile\/{id}",
        "name": null,
        "action": "App\\Http\\Controllers\\DriverDashboardController@driver_update_profile",
        "middleware": "web,locale,driver_guest"
    }, {
        "domain": null,
        "method": "GET|HEAD",
        "uri": "facebookAuthenticate",
        "name": null,
        "action": "App\\Http\\Controllers\\UserController@facebookAuthenticate",
        "middleware": "web,locale"
    }, {
        "domain": null,
        "method": "GET|HEAD",
        "uri": "facebook_login",
        "name": null,
        "action": "App\\Http\\Controllers\\UserController@facebook_login",
        "middleware": "web,locale"
    }, {
        "domain": null,
        "method": "GET|HEAD",
        "uri": "forgot_password_company",
        "name": null,
        "action": "App\\Http\\Controllers\\UserController@forgot_password",
        "middleware": "web,locale"
    }, {
        "domain": null,
        "method": "GET|HEAD",
        "uri": "forgot_password_driver",
        "name": null,
        "action": "App\\Http\\Controllers\\UserController@forgot_password",
        "middleware": "web,locale"
    }, {
        "domain": null,
        "method": "GET|HEAD",
        "uri": "forgot_password_link\/{id}",
        "name": null,
        "action": "App\\Http\\Controllers\\EmailController@forgot_password_link",
        "middleware": "web,locale"
    }, {
        "domain": null,
        "method": "GET|HEAD",
        "uri": "forgot_password_rider",
        "name": null,
        "action": "App\\Http\\Controllers\\UserController@forgot_password",
        "middleware": "web,locale"
    }, {
        "domain": null,
        "method": "POST",
        "uri": "forgotpassword",
        "name": null,
        "action": "App\\Http\\Controllers\\UserController@forgotpassword",
        "middleware": "web,locale"
    }, {
        "domain": null,
        "method": "GET|HEAD",
        "uri": "googleAuthenticate",
        "name": null,
        "action": "App\\Http\\Controllers\\UserController@googleAuthenticate",
        "middleware": "web,locale"
    }, {
        "domain": null,
        "method": "GET|HEAD",
        "uri": "help",
        "name": null,
        "action": "App\\Http\\Controllers\\HomeController@help",
        "middleware": "web,locale"
    }, {
        "domain": null,
        "method": "GET|HEAD",
        "uri": "help\/article\/{id}\/{question}",
        "name": null,
        "action": "App\\Http\\Controllers\\HomeController@help",
        "middleware": "web,locale"
    }, {
        "domain": null,
        "method": "GET|HEAD",
        "uri": "help\/topic\/{id}\/{category}",
        "name": null,
        "action": "App\\Http\\Controllers\\HomeController@help",
        "middleware": "web,locale"
    }, {
        "domain": null,
        "method": "GET|HEAD",
        "uri": "how_it_works",
        "name": null,
        "action": "App\\Http\\Controllers\\RideController@how_it_works",
        "middleware": "web,locale"
    }, {
        "domain": null,
        "method": "GET|HEAD",
        "uri": "install",
        "name": "LaravelInstaller::welcome",
        "action": "RachidLaasri\\LaravelInstaller\\Controllers\\WelcomeController@welcome",
        "middleware": "web,install"
    }, {
        "domain": null,
        "method": "GET|HEAD",
        "uri": "install\/database",
        "name": "LaravelInstaller::database",
        "action": "RachidLaasri\\LaravelInstaller\\Controllers\\DatabaseController@database",
        "middleware": "web,install"
    }, {
        "domain": null,
        "method": "GET|HEAD",
        "uri": "install\/environment",
        "name": "LaravelInstaller::environment",
        "action": "RachidLaasri\\LaravelInstaller\\Controllers\\EnvironmentController@environmentMenu",
        "middleware": "web,install"
    }, {
        "domain": null,
        "method": "GET|HEAD",
        "uri": "install\/environment\/classic",
        "name": "LaravelInstaller::environmentClassic",
        "action": "RachidLaasri\\LaravelInstaller\\Controllers\\EnvironmentController@environmentClassic",
        "middleware": "web,install"
    }, {
        "domain": null,
        "method": "POST",
        "uri": "install\/environment\/saveClassic",
        "name": "LaravelInstaller::environmentSaveClassic",
        "action": "RachidLaasri\\LaravelInstaller\\Controllers\\EnvironmentController@saveClassic",
        "middleware": "web,install"
    }, {
        "domain": null,
        "method": "POST",
        "uri": "install\/environment\/saveWizard",
        "name": "LaravelInstaller::environmentSaveWizard",
        "action": "RachidLaasri\\LaravelInstaller\\Controllers\\EnvironmentController@saveWizard",
        "middleware": "web,install"
    }, {
        "domain": null,
        "method": "GET|HEAD",
        "uri": "install\/environment\/wizard",
        "name": "LaravelInstaller::environmentWizard",
        "action": "RachidLaasri\\LaravelInstaller\\Controllers\\EnvironmentController@environmentWizard",
        "middleware": "web,install"
    }, {
        "domain": null,
        "method": "GET|HEAD",
        "uri": "install\/final",
        "name": "LaravelInstaller::final",
        "action": "RachidLaasri\\LaravelInstaller\\Controllers\\FinalController@finish",
        "middleware": "web,install"
    }, {
        "domain": null,
        "method": "GET|HEAD",
        "uri": "install\/permissions",
        "name": "LaravelInstaller::permissions",
        "action": "RachidLaasri\\LaravelInstaller\\Controllers\\PermissionsController@permissions",
        "middleware": "web,install"
    }, {
        "domain": null,
        "method": "GET|HEAD",
        "uri": "install\/requirements",
        "name": "LaravelInstaller::requirements",
        "action": "RachidLaasri\\LaravelInstaller\\Controllers\\RequirementsController@requirements",
        "middleware": "web,install"
    }, {
        "domain": null,
        "method": "GET|HEAD",
        "uri": "invoice_download\/{id}",
        "name": null,
        "action": "App\\Http\\Controllers\\DashboardController@invoice_download",
        "middleware": "web,locale,rider_guest"
    }, {
        "domain": null,
        "method": "POST",
        "uri": "login",
        "name": null,
        "action": "App\\Http\\Controllers\\UserController@login",
        "middleware": "web,locale"
    }, {
        "domain": null,
        "method": "POST",
        "uri": "login_driver",
        "name": null,
        "action": "App\\Http\\Controllers\\UserController@login_driver",
        "middleware": "web,locale"
    }, {
        "domain": null,
        "method": "GET|HEAD",
        "uri": "oweAmount",
        "name": null,
        "action": "App\\Http\\Controllers\\Api\\RatingController@oweAmount",
        "middleware": "web"
    }, {
        "domain": null,
        "method": "GET|HEAD",
        "uri": "payment",
        "name": null,
        "action": "App\\Http\\Controllers\\DashboardController@payment",
        "middleware": "web,locale,rider_guest"
    }, {
        "domain": null,
        "method": "GET|HEAD",
        "uri": "payout_default\/{id}",
        "name": null,
        "action": "App\\Http\\Controllers\\UserController@payout_default",
        "middleware": "web,locale,driver_guest"
    }, {
        "domain": null,
        "method": "GET|HEAD",
        "uri": "payout_delete\/{id}",
        "name": null,
        "action": "App\\Http\\Controllers\\UserController@payout_delete",
        "middleware": "web,locale,driver_guest"
    }, {
        "domain": null,
        "method": "GET|POST|HEAD",
        "uri": "payout_preferences\/{id}",
        "name": null,
        "action": "App\\Http\\Controllers\\UserController@payout_preferences",
        "middleware": "web,locale,driver_guest"
    }, {
        "domain": null,
        "method": "GET|HEAD",
        "uri": "print_invoice\/{id}",
        "name": null,
        "action": "App\\Http\\Controllers\\DriverDashboardController@print_invoice",
        "middleware": "web,locale"
    }, {
        "domain": null,
        "method": "GET|HEAD",
        "uri": "profile",
        "name": null,
        "action": "App\\Http\\Controllers\\DashboardController@profile",
        "middleware": "web,locale,rider_guest"
    }, {
        "domain": null,
        "method": "POST",
        "uri": "profile_upload",
        "name": null,
        "action": "App\\Http\\Controllers\\DriverDashboardController@profile_upload",
        "middleware": "web,locale"
    }, {
        "domain": null,
        "method": "GET|HEAD",
        "uri": "requirements",
        "name": null,
        "action": "App\\Http\\Controllers\\DriveController@requirements",
        "middleware": "web,locale"
    }, {
        "domain": null,
        "method": "GET|POST|HEAD",
        "uri": "reset_password",
        "name": null,
        "action": "App\\Http\\Controllers\\UserController@reset_password",
        "middleware": "web,locale"
    }, {
        "domain": null,
        "method": "GET|HEAD",
        "uri": "ride",
        "name": null,
        "action": "App\\Http\\Controllers\\RideController@ride",
        "middleware": "web,locale"
    }, {
        "domain": null,
        "method": "POST",
        "uri": "rider_rating\/{rating}\/{trip_id}",
        "name": null,
        "action": "App\\Http\\Controllers\\DashboardController@rider_rating",
        "middleware": "web,locale,rider_guest"
    }, {
        "domain": null,
        "method": "POST",
        "uri": "rider_register",
        "name": null,
        "action": "App\\Http\\Controllers\\UserController@rider_register",
        "middleware": "web,locale"
    }, {
        "domain": null,
        "method": "POST",
        "uri": "rider_update_profile\/{id}",
        "name": null,
        "action": "App\\Http\\Controllers\\DashboardController@update_profile",
        "middleware": "web,locale,rider_guest"
    }, {
        "domain": null,
        "method": "GET|HEAD",
        "uri": "safety",
        "name": null,
        "action": "App\\Http\\Controllers\\RideController@safety",
        "middleware": "web,locale"
    }, {
        "domain": null,
        "method": "POST",
        "uri": "set_session",
        "name": null,
        "action": "App\\Http\\Controllers\\HomeController@set_session",
        "middleware": "web,locale"
    }, {
        "domain": null,
        "method": "GET|HEAD",
        "uri": "sign_out",
        "name": null,
        "action": "Closure",
        "middleware": "web"
    }, {
        "domain": null,
        "method": "GET|HEAD",
        "uri": "signin",
        "name": null,
        "action": "App\\Http\\Controllers\\UserController@signin",
        "middleware": "web,locale"
    }, {
        "domain": null,
        "method": "GET|POST|HEAD",
        "uri": "signin_company",
        "name": null,
        "action": "App\\Http\\Controllers\\UserController@signin_company",
        "middleware": "web,locale"
    }, {
        "domain": null,
        "method": "GET|POST|HEAD",
        "uri": "signin_driver",
        "name": null,
        "action": "App\\Http\\Controllers\\UserController@signin_driver",
        "middleware": "web,locale"
    }, {
        "domain": null,
        "method": "GET|POST|HEAD",
        "uri": "signin_rider",
        "name": null,
        "action": "App\\Http\\Controllers\\UserController@signin_rider",
        "middleware": "web,locale"
    }, {
        "domain": null,
        "method": "GET|HEAD",
        "uri": "signup",
        "name": null,
        "action": "App\\Http\\Controllers\\UserController@signup",
        "middleware": "web,locale"
    }, {
        "domain": null,
        "method": "GET|POST|HEAD",
        "uri": "signup_company",
        "name": null,
        "action": "App\\Http\\Controllers\\UserController@signup_company",
        "middleware": "web,locale"
    }, {
        "domain": null,
        "method": "GET|POST|HEAD",
        "uri": "signup_driver",
        "name": null,
        "action": "App\\Http\\Controllers\\UserController@signup_driver",
        "middleware": "web,locale"
    }, {
        "domain": null,
        "method": "GET|POST|HEAD",
        "uri": "signup_rider",
        "name": null,
        "action": "App\\Http\\Controllers\\UserController@signup_rider",
        "middleware": "web,locale"
    }, {
        "domain": null,
        "method": "GET|POST|HEAD",
        "uri": "stripe_payout_preferences",
        "name": null,
        "action": "App\\Http\\Controllers\\UserController@stripe_payout_preferences",
        "middleware": "web,locale,driver_guest"
    }, {
        "domain": null,
        "method": "GET|HEAD",
        "uri": "trip",
        "name": null,
        "action": "App\\Http\\Controllers\\DashboardController@trip",
        "middleware": "web,locale,rider_guest"
    }, {
        "domain": null,
        "method": "POST",
        "uri": "trip_detail\/rider_rating\/{rating}\/{trip_id}",
        "name": null,
        "action": "App\\Http\\Controllers\\DashboardController@rider_rating",
        "middleware": "web,locale,rider_guest"
    }, {
        "domain": null,
        "method": "GET|HEAD",
        "uri": "trip_detail\/{id}",
        "name": null,
        "action": "App\\Http\\Controllers\\DashboardController@trip_detail",
        "middleware": "web,locale,rider_guest"
    }, {
        "domain": null,
        "method": "GET|HEAD",
        "uri": "trip_invoice\/{id}",
        "name": null,
        "action": "App\\Http\\Controllers\\DashboardController@trip_invoice",
        "middleware": "web,locale,rider_guest"
    }, {
        "domain": null,
        "method": "GET|HEAD",
        "uri": "update",
        "name": "LaravelUpdater::welcome",
        "action": "RachidLaasri\\LaravelInstaller\\Controllers\\UpdateController@welcome",
        "middleware": "web,update"
    }, {
        "domain": null,
        "method": "GET|HEAD",
        "uri": "update\/database",
        "name": "LaravelUpdater::database",
        "action": "RachidLaasri\\LaravelInstaller\\Controllers\\UpdateController@database",
        "middleware": "web,update"
    }, {
        "domain": null,
        "method": "GET|HEAD",
        "uri": "update\/final",
        "name": "LaravelUpdater::final",
        "action": "RachidLaasri\\LaravelInstaller\\Controllers\\UpdateController@finish",
        "middleware": "web"
    }, {
        "domain": null,
        "method": "GET|HEAD",
        "uri": "update\/overview",
        "name": "LaravelUpdater::overview",
        "action": "RachidLaasri\\LaravelInstaller\\Controllers\\UpdateController@overview",
        "middleware": "web,update"
    }, {
        "domain": null,
        "method": "GET|POST|HEAD",
        "uri": "update_payout_preferences\/{id}",
        "name": null,
        "action": "App\\Http\\Controllers\\UserController@update_payout_preferences",
        "middleware": "web,locale,driver_guest"
    }, {
        "domain": null,
        "method": "GET|HEAD",
        "uri": "user_disabled",
        "name": null,
        "action": "App\\Http\\Controllers\\UserController@user_disabled",
        "middleware": "web,locale"
    }, {
        "domain": null,
        "method": "GET|HEAD",
        "uri": "{name}",
        "name": null,
        "action": "App\\Http\\Controllers\\HomeController@static_pages",
        "middleware": "web"
    }]
